miamcpdoc/__init__.py
miamcpdoc/_version.py
miamcpdoc/aisdk_docs_mcp.py
miamcpdoc/ascii_art.txt
miamcpdoc/cli.py
miamcpdoc/creative_frameworks_mcp.py
miamcpdoc/default_config.yaml
miamcpdoc/huggingface_docs_mcp.py
miamcpdoc/langgraph.py
miamcpdoc/langgraph_docs_mcp.py
miamcpdoc/main.py
miamcpdoc/mcp_server_docs_mcp.py
miamcpdoc/splash.py
miamcpdoc/structural_guidance_mcp.py
miamcpdoc/technical_guidance_mcp.py
miamcpdoc/what_is_llms_mcp.py
miamcpdoc/__llms/MCP_DOCUMENTATION_STRATEGY.md
miamcpdoc/__llms/README.md
miamcpdoc/__llms/llms-ava8-embodiment.gemini.md
miamcpdoc/__llms/llms-claude-sdk.gemini.md
miamcpdoc/__llms/llms-creative-orientation.txt
miamcpdoc/__llms/llms-delayed-resolution-principle.md
miamcpdoc/__llms/llms-digital-decision-making.md
miamcpdoc/__llms/llms-duo-mia-miette-arc-v8.md
miamcpdoc/__llms/llms-duo-mia-miette-arc-v9-proposal.md
miamcpdoc/__llms/llms-haiku-ripple-embodiment.md
miamcpdoc/__llms/llms-leadership.txt
miamcpdoc/__llms/llms-managerial-moment-of-truth.md
miamcpdoc/__llms/llms-narrative-remixing.txt
miamcpdoc/__llms/llms-non-creative-orientation-approach-to-convert.txt
miamcpdoc/__llms/llms-pythonista-full.gemini.txt
miamcpdoc/__llms/llms-rise-framework-full.txt
miamcpdoc/__llms/llms-rise-framework.txt
miamcpdoc/__llms/llms-structural-distillation.txt
miamcpdoc/__llms/llms-structural-tension-charts.txt
miamcpdoc/__llms/llms-structural-thinking-persona-capabilities.txt
miamcpdoc/__llms/llms-structural-thinking.claude.f04dc696-3959-4be4-ad3f-390df0f517d9.txt
miamcpdoc/__llms/llms-structural-thinking.gemini.txt
miamcpdoc/__llms/llms-tryad-mia-miette-ripple-full.gemini.md
miamcpdoc/__llms/llms-txt-compliance-checklist.md
miamcpdoc/__llms/llms-ui-pythonista-guide.gemini.txt
miamcpdoc/__llms/llms-vercel-build-integrity.gemini.md
miamcpdoc/mcp_server_docs/llms-miadi-mcp-server.txt
miamcpdoc-0.0.45.dist-info/METADATA
miamcpdoc-0.0.45.dist-info/WHEEL
miamcpdoc-0.0.45.dist-info/entry_points.txt
miamcpdoc-0.0.45.dist-info/licenses/LICENSE
miamcpdoc-0.0.45.dist-info/RECORD
