Metadata-Version: 2.4
Name: miamcpdoc
Version: 0.0.45
Summary: Mia's Server llms-txt documentation over MCP
License-Expression: MIT
License-File: LICENSE
Requires-Python: >=3.10
Requires-Dist: httpcore>=1.0.5
Requires-Dist: httpx>=0.28.1
Requires-Dist: markdownify>=1.1.0
Requires-Dist: mcp[cli]>=1.4.1
Requires-Dist: pyyaml>=6.0.1
